{"ID":"3c97151a-28db-4830-94e2-2a7776b1e7ea","Enabled":true,"GameBoard":{"boardSpaceData":[{"P":"0","T":["B"]},{"P":"0","T":["S"]},{"P":"0","T":[]},{"P":"1","T":["S"]},{"P":"2","T":[]},{"P":"0","T":[]},{"P":"0","T":["S"]},{"P":"0","T":["B"]},{"P":"0","T":["S"]},{"P":"0","T":[]},{"P":"0","T":[]},{"P":"2","T":[]},{"P":"2","T":["S"]},{"P":"0","T":[]},{"P":"0","T":[]},{"P":"0","T":["S"]},{"P":"0","T":[]},{"P":"0","T":[]},{"P":"0","T":["S"]},{"P":"0","T":[]},{"P":"0","T":[]},{"P":"1","T":["S"]},{"P":"0","T":[]},{"P":"0","T":[]},{"P":"0","T":[]},{"P":"0","T":[]},{"P":"2","T":[]},{"P":"1","T":["S"]},{"P":"1","T":[]},{"P":"1","T":[]},{"P":"2","T":["S"]},{"P":"1","T":[]},{"P":"1","T":[]},{"P":"2","T":["S"]},{"P":"0","T":[]},{"P":"0","T":[]},{"P":"1","T":["S"]},{"P":"2","T":[]},{"P":"0","T":[]},{"P":"0","T":[]},{"P":"0","T":[]},{"P":"0","T":[]},{"P":"0","T":["S"]},{"P":"0","T":[]},{"P":"0","T":[]},{"P":"2","T":["S"]},{"P":"0","T":[]},{"P":"0","T":[]},{"P":"0","T":["S"]},{"P":"0","T":[]},{"P":"0","T":[]},{"P":"2","T":["S"]},{"P":"0","T":[]},{"P":"0","T":[]},{"P":"0","T":[]},{"P":"0","T":["S"]},{"P":"0","T":["B"]},{"P":"0","T":["S"]},{"P":"0","T":[]},{"P":"0","T":[]},{"P":"1","T":["S"]},{"P":"0","T":[]},{"P":"0","T":["S"]},{"P":"0","T":["B"]}],"initialMoves":[],"rows":8,"columns":8,"area":2,"id":"99678a2d-2977-4a22-8b3a-857d90fcebee","boardName":"TRAINING_GARDEN Win In 2","enabled":true,"enabledGallery":false,"enabledRealtime":false},"Profile":0,"Boss":0,"FirstTurn":0,"Solution":[{"playerId":1,"playerString":null,"moves":[{"piece":{"conditions":[],"playerId":1,"herdId":0,"UniqueId":"758ad76f-86d9-498a-8e0d-52b1ebe193fb","pieceType":0,"Notation":"1"},"direction":0,"location":4,"moveType":0,"notation":"Move:UP4"}],"Notation":"Move:UP4","timestamp":0,"uniqueId":"027dc183-0541-4d66-aecb-ef6039378137"},{"playerId":1,"playerString":null,"moves":[{"piece":{"conditions":[],"playerId":1,"herdId":0,"UniqueId":"8c0e1f4b-83e9-45de-ac1c-469bb8286522","pieceType":0,"Notation":"1"},"direction":0,"location":4,"moveType":0,"notation":"Move:UP4"}],"Notation":"Move:UP4","timestamp":0,"uniqueId":"7158deaf-4329-4de0-be6f-41c2e69c1a58"}],"SolutionStateData":{"boardSpaceData":[{"P":"0","T":["B"]},{"P":"0","T":["S"]},{"P":"0","T":[]},{"P":"1","T":["S"]},{"P":"2","T":[]},{"P":"0","T":[]},{"P":"0","T":["S"]},{"P":"0","T":["B"]},{"P":"0","T":["S"]},{"P":"0","T":[]},{"P":"0","T":[]},{"P":"2","T":[]},{"P":"2","T":["S"]},{"P":"0","T":[]},{"P":"0","T":[]},{"P":"0","T":["S"]},{"P":"0","T":[]},{"P":"0","T":[]},{"P":"0","T":["S"]},{"P":"0","T":[]},{"P":"0","T":[]},{"P":"1","T":["S"]},{"P":"0","T":[]},{"P":"0","T":[]},{"P":"0","T":[]},{"P":"0","T":[]},{"P":"2","T":[]},{"P":"1","T":["S"]},{"P":"1","T":[]},{"P":"1","T":[]},{"P":"2","T":["S"]},{"P":"1","T":[]},{"P":"1","T":[]},{"P":"2","T":["S"]},{"P":"0","T":[]},{"P":"0","T":[]},{"P":"1","T":["S"]},{"P":"2","T":[]},{"P":"2","T":[]},{"P":"0","T":[]},{"P":"0","T":[]},{"P":"0","T":[]},{"P":"0","T":["S"]},{"P":"0","T":[]},{"P":"1","T":[]},{"P":"2","T":["S"]},{"P":"0","T":[]},{"P":"0","T":[]},{"P":"0","T":["S"]},{"P":"0","T":[]},{"P":"0","T":[]},{"P":"2","T":["S"]},{"P":"1","T":[]},{"P":"0","T":[]},{"P":"0","T":[]},{"P":"0","T":["S"]},{"P":"0","T":["B"]},{"P":"0","T":["S"]},{"P":"0","T":[]},{"P":"0","T":[]},{"P":"1","T":["S"]},{"P":"0","T":[]},{"P":"0","T":["S"]},{"P":"0","T":["B"]}],"rows":8,"columns":8,"area":2},"GoalType":0,"MoveLimit":2,"Complexity":1688,"StartingMagic":0,"AvailableSpells":[]}