{"boardSpaceData":[{"P":"0","T":["B"]},{"P":"0","T":[]},{"P":"0","T":[]},{"P":"0","T":[]},{"P":"0","T":[]},{"P":"0","T":[]},{"P":"0","T":[]},{"P":"0","T":["B"]},{"P":"0","T":[]},{"P":"0","T":[]},{"P":"0","T":[]},{"P":"0","T":[]},{"P":"0","T":[]},{"P":"0","T":[]},{"P":"0","T":[]},{"P":"0","T":[]},{"P":"1","T":["AL"]},{"P":"2","T":[]},{"P":"2","T":["S"]},{"P":"1","T":["S"]},{"P":"1","T":["S"]},{"P":"1","T":["S"]},{"P":"2","T":[]},{"P":"0","T":[]},{"P":"-1","T":[]},{"P":"1","T":["AL"]},{"P":"1","T":["S"]},{"P":"1","T":["S"]},{"P":"0","T":["S"]},{"P":"2","T":["S"]},{"P":"2","T":[]},{"P":"0","T":[]},{"P":"0","T":[]},{"P":"1","T":[]},{"P":"2","T":["AL"]},{"P":"2","T":["S"]},{"P":"0","T":["S"]},{"P":"1","T":["S"]},{"P":"0","T":[]},{"P":"0","T":[]},{"P":"2","T":[]},{"P":"1","T":[]},{"P":"2","T":["S"]},{"P":"0","T":["AL"]},{"P":"0","T":["S"]},{"P":"2","T":["S"]},{"P":"0","T":[]},{"P":"0","T":[]},{"P":"0","T":[]},{"P":"0","T":[]},{"P":"0","T":[]},{"P":"0","T":[]},{"P":"0","T":["AL"]},{"P":"1","T":[]},{"P":"0","T":[]},{"P":"0","T":[]},{"P":"0","T":["B"]},{"P":"2","T":[]},{"P":"1","T":[]},{"P":"2","T":[]},{"P":"1","T":[]},{"P":"2","T":["AL"]},{"P":"0","T":[]},{"P":"0","T":["B"]}],"initialMoves":[],"rows":8,"columns":8,"area":2,"id":"421cdc18-8fd2-428b-ae7e-de2bd0f2a358","boardName":"TRAINING_GARDEN 119 Win In 1 ActivePlayer=1","enabled":true,"enabledGallery":false,"enabledRealtime":false}