{"boardSpaceData":[{"P":null,"T":["B"]},{"P":null,"T":null},{"P":null,"T":null},{"P":null,"T":null},{"P":null,"T":null},{"P":null,"T":null},{"P":null,"T":null},{"P":null,"T":["B"]},{"P":null,"T":null},{"P":null,"T":null},{"P":null,"T":["oRH010"]},{"P":null,"T":null},{"P":null,"T":null},{"P":null,"T":null},{"P":null,"T":null},{"P":null,"T":null},{"P":null,"T":["i"]},{"P":null,"T":["i"]},{"P":null,"T":["i"]},{"P":null,"T":["i"]},{"P":null,"T":["I"]},{"P":null,"T":["i"]},{"P":null,"T":["0"]},{"P":null,"T":["i"]},{"P":null,"T":["i"]},{"P":null,"T":["0"]},{"P":null,"T":["i"]},{"P":null,"T":["i"]},{"P":null,"T":["I"]},{"P":null,"T":["i"]},{"P":null,"T":["i"]},{"P":null,"T":["i"]},{"P":null,"T":["i"]},{"P":null,"T":["i"]},{"P":null,"T":["i"]},{"P":null,"T":["i"]},{"P":null,"T":["I"]},{"P":null,"T":["i"]},{"P":null,"T":["0"]},{"P":null,"T":["i"]},{"P":null,"T":["i"]},{"P":null,"T":["0"]},{"P":null,"T":["i"]},{"P":null,"T":["i"]},{"P":null,"T":["I"]},{"P":null,"T":["i"]},{"P":null,"T":["i"]},{"P":null,"T":["i"]},{"P":null,"T":null},{"P":null,"T":null},{"P":null,"T":null},{"P":null,"T":null},{"P":null,"T":null},{"P":null,"T":null},{"P":null,"T":["oLH010"]},{"P":null,"T":null},{"P":null,"T":["B"]},{"P":null,"T":null},{"P":null,"T":null},{"P":null,"T":null},{"P":null,"T":null},{"P":null,"T":null},{"P":null,"T":null},{"P":null,"T":["B"]}],"initialMoves":[],"rows":8,"columns":8,"area":16,"id":"632e0eae-0a5e-4391-b33d-1fb24f2f18ab","boardName":"IceExplode","enabled":true,"enabledGallery":true,"enabledRealtime":true}