{"boardSpaceData":[{"P":"0","T":["B"]},{"P":"0","T":["G"]},{"P":"0","T":[]},{"P":"0","T":[]},{"P":"2","T":[]},{"P":"0","T":[]},{"P":"0","T":[]},{"P":"0","T":["B"]},{"P":"0","T":[]},{"P":"0","T":[]},{"P":"0","T":[]},{"P":"1","T":[]},{"P":"1","T":[]},{"P":"0","T":[]},{"P":"0","T":[]},{"P":"0","T":["G"]},{"P":"0","T":[]},{"P":"0","T":[]},{"P":"0","T":[]},{"P":"2","T":[]},{"P":"1","T":[]},{"P":"0","T":[]},{"P":"0","T":[]},{"P":"0","T":[]},{"P":"0","T":[]},{"P":"0","T":["AR"]},{"P":"2","T":["AD"]},{"P":"1","T":[]},{"P":"1","T":[]},{"P":"1","T":[]},{"P":"2","T":[]},{"P":"0","T":[]},{"P":"0","T":[]},{"P":"-1","T":["AU"]},{"P":"1","T":["AL"]},{"P":"0","T":[]},{"P":"2","T":[]},{"P":"1","T":[]},{"P":"2","T":[]},{"P":"0","T":[]},{"P":"0","T":[]},{"P":"2","T":[]},{"P":"0","T":[]},{"P":"0","T":[]},{"P":"0","T":[]},{"P":"2","T":[]},{"P":"1","T":[]},{"P":"0","T":[]},{"P":"0","T":["G"]},{"P":"0","T":[]},{"P":"0","T":[]},{"P":"0","T":[]},{"P":"0","T":[]},{"P":"2","T":[]},{"P":"0","T":[]},{"P":"0","T":[]},{"P":"0","T":["B"]},{"P":"0","T":[]},{"P":"0","T":[]},{"P":"0","T":[]},{"P":"0","T":[]},{"P":"0","T":[]},{"P":"0","T":["G"]},{"P":"0","T":["B"]}],"initialMoves":[],"rows":8,"columns":8,"area":4,"id":"d67c1e30-db5a-4eef-ad71-66b591430b9c","boardName":"ENCHANTED_FOREST 115 Win In 1 ActivePlayer=1","enabled":true,"enabledGallery":false,"enabledRealtime":false}