{"boardSpaceData":[{"P":"0","T":["B"]},{"P":"0","T":["~"]},{"P":"0","T":["~"]},{"P":"0","T":["~"]},{"P":"2","T":["~"]},{"P":"2","T":[]},{"P":"1","T":[]},{"P":"0","T":["B"]},{"P":"0","T":[]},{"P":"0","T":["~"]},{"P":"0","T":["~"]},{"P":"0","T":["~"]},{"P":"1","T":["~"]},{"P":"1","T":[]},{"P":"2","T":[]},{"P":"0","T":[]},{"P":"0","T":[]},{"P":"0","T":["~"]},{"P":"0","T":["~"]},{"P":"0","T":["~"]},{"P":"0","T":["~"]},{"P":"1","T":[]},{"P":"0","T":["G"]},{"P":"0","T":[]},{"P":"0","T":[]},{"P":"0","T":["~","G"]},{"P":"1","T":["~"]},{"P":"1","T":["~"]},{"P":"0","T":["T"]},{"P":"0","T":[]},{"P":"2","T":[]},{"P":"0","T":["T"]},{"P":"0","T":[]},{"P":"0","T":["~"]},{"P":"0","T":["~"]},{"P":"0","T":["~"]},{"P":"2","T":["~"]},{"P":"0","T":[]},{"P":"1","T":[]},{"P":"0","T":[]},{"P":"0","T":[]},{"P":"-1","T":["~"]},{"P":"0","T":["~"]},{"P":"0","T":["~"]},{"P":"0","T":["~"]},{"P":"0","T":["G"]},{"P":"0","T":[]},{"P":"0","T":[]},{"P":"0","T":[]},{"P":"0","T":["~","G"]},{"P":"2","T":["~"]},{"P":"0","T":["~"]},{"P":"0","T":["T"]},{"P":"0","T":[]},{"P":"0","T":[]},{"P":"0","T":["T"]},{"P":"0","T":["B"]},{"P":"2","T":["~"]},{"P":"0","T":["~"]},{"P":"0","T":["~"]},{"P":"0","T":["~"]},{"P":"0","T":[]},{"P":"0","T":[]},{"P":"0","T":["B"]}],"initialMoves":[],"rows":8,"columns":8,"area":4,"id":"9c463b17-95a8-479e-9e3e-395f0a03f61f","boardName":"ENCHANTED_FOREST 141 Win In 1 ActivePlayer=1","enabled":true,"enabledGallery":false,"enabledRealtime":false}