{"boardSpaceData":[{"P":"0","T":["B"]},{"P":"-1","T":[]},{"P":"0","T":[]},{"P":"0","T":["AD"]},{"P":"0","T":[]},{"P":"0","T":[]},{"P":"0","T":[]},{"P":"0","T":["B"]},{"P":"0","T":[]},{"P":"0","T":["X"]},{"P":"0","T":[]},{"P":"0","T":[]},{"P":"0","T":[]},{"P":"0","T":[]},{"P":"0","T":[]},{"P":"0","T":[]},{"P":"0","T":[]},{"P":"0","T":[]},{"P":"0","T":["X"]},{"P":"0","T":[]},{"P":"0","T":[]},{"P":"0","T":[]},{"P":"0","T":[]},{"P":"0","T":[]},{"P":"0","T":[]},{"P":"0","T":[]},{"P":"0","T":[]},{"P":"0","T":["X"]},{"P":"0","T":[]},{"P":"0","T":[]},{"P":"2","T":[]},{"P":"0","T":["AL"]},{"P":"0","T":["AR"]},{"P":"0","T":[]},{"P":"0","T":[]},{"P":"0","T":[]},{"P":"0","T":["X"]},{"P":"0","T":[]},{"P":"2","T":[]},{"P":"1","T":[]},{"P":"0","T":[]},{"P":"0","T":[]},{"P":"0","T":[]},{"P":"0","T":[]},{"P":"0","T":[]},{"P":"0","T":["X"]},{"P":"0","T":[]},{"P":"1","T":[]},{"P":"0","T":[]},{"P":"0","T":[]},{"P":"0","T":[]},{"P":"0","T":[]},{"P":"0","T":[]},{"P":"0","T":[]},{"P":"0","T":["X"]},{"P":"0","T":[]},{"P":"0","T":["B"]},{"P":"0","T":[]},{"P":"0","T":[]},{"P":"0","T":[]},{"P":"0","T":["AU"]},{"P":"0","T":[]},{"P":"0","T":[]},{"P":"0","T":["B"]}],"initialMoves":[],"rows":8,"columns":8,"area":4,"id":"5e65951f-ffe9-4623-b2eb-8ad46509b5c6","boardName":"ENCHANTED_FOREST 16 Win In 2 ActivePlayer=1","enabled":true,"enabledGallery":false,"enabledRealtime":false}