{"boardSpaceData":[{"P":"0","T":["B"]},{"P":"0","T":[]},{"P":"0","T":[]},{"P":"0","T":[]},{"P":"0","T":[]},{"P":"0","T":[]},{"P":"0","T":[]},{"P":"0","T":["B"]},{"P":"0","T":[]},{"P":"0","T":["X"]},{"P":"0","T":[]},{"P":"0","T":[]},{"P":"0","T":[]},{"P":"0","T":[]},{"P":"0","T":[]},{"P":"0","T":[]},{"P":"0","T":[]},{"P":"0","T":[]},{"P":"0","T":["X"]},{"P":"0","T":[]},{"P":"0","T":[]},{"P":"0","T":[]},{"P":"0","T":[]},{"P":"0","T":[]},{"P":"0","T":[]},{"P":"0","T":[]},{"P":"0","T":[]},{"P":"0","T":["X"]},{"P":"0","T":[]},{"P":"0","T":[]},{"P":"0","T":[]},{"P":"0","T":[]},{"P":"0","T":[]},{"P":"0","T":[]},{"P":"0","T":[]},{"P":"0","T":[]},{"P":"0","T":["X"]},{"P":"0","T":[]},{"P":"0","T":[]},{"P":"1","T":[]},{"P":"0","T":[]},{"P":"0","T":[]},{"P":"0","T":[]},{"P":"0","T":[]},{"P":"0","T":[]},{"P":"0","T":["X"]},{"P":"0","T":[]},{"P":"0","T":[]},{"P":"0","T":[]},{"P":"0","T":[]},{"P":"0","T":[]},{"P":"0","T":[]},{"P":"0","T":[]},{"P":"0","T":[]},{"P":"0","T":["X"]},{"P":"0","T":[]},{"P":"0","T":["B"]},{"P":"0","T":[]},{"P":"0","T":[]},{"P":"0","T":[]},{"P":"2","T":[]},{"P":"0","T":[]},{"P":"0","T":[]},{"P":"0","T":["B"]}],"initialMoves":[],"rows":8,"columns":8,"area":4,"id":"766eb4fb-59aa-4964-86f6-54a9b9ddb10e","boardName":"ENCHANTED_FOREST Win In 3","enabled":true,"enabledGallery":false,"enabledRealtime":false}