{"boardSpaceData":[{"P":"0","T":["B"]},{"P":"-1","T":[]},{"P":"0","T":[]},{"P":"0","T":[]},{"P":"0","T":["G"]},{"P":"2","T":[]},{"P":"0","T":[]},{"P":"0","T":["B"]},{"P":"0","T":[]},{"P":"0","T":[]},{"P":"0","T":[]},{"P":"2","T":[]},{"P":"1","T":[]},{"P":"0","T":[]},{"P":"0","T":[]},{"P":"0","T":[]},{"P":"0","T":[]},{"P":"2","T":[]},{"P":"2","T":[]},{"P":"1","T":[]},{"P":"0","T":[]},{"P":"0","T":[]},{"P":"0","T":[]},{"P":"0","T":[]},{"P":"0","T":[]},{"P":"0","T":[]},{"P":"1","T":[]},{"P":"0","T":[]},{"P":"0","T":["G"]},{"P":"0","T":[]},{"P":"0","T":["G"]},{"P":"0","T":[]},{"P":"0","T":[]},{"P":"2","T":[]},{"P":"1","T":[]},{"P":"1","T":[]},{"P":"0","T":[]},{"P":"0","T":[]},{"P":"0","T":[]},{"P":"0","T":[]},{"P":"0","T":[]},{"P":"0","T":["G"]},{"P":"0","T":[]},{"P":"2","T":[]},{"P":"1","T":[]},{"P":"0","T":[]},{"P":"0","T":[]},{"P":"0","T":[]},{"P":"0","T":[]},{"P":"0","T":[]},{"P":"0","T":[]},{"P":"0","T":[]},{"P":"0","T":[]},{"P":"0","T":[]},{"P":"0","T":[]},{"P":"0","T":[]},{"P":"0","T":["B"]},{"P":"0","T":[]},{"P":"0","T":[]},{"P":"0","T":[]},{"P":"0","T":[]},{"P":"0","T":[]},{"P":"0","T":[]},{"P":"0","T":["B"]}],"initialMoves":[],"rows":8,"columns":8,"area":4,"id":"3cc30930-877d-45f0-ac4a-8beeb6e0de4f","boardName":"ENCHANTED_FOREST 61 Win In 3 ActivePlayer=1","enabled":true,"enabledGallery":false,"enabledRealtime":false}