{"ID":"3cd84d8d-fe94-43a1-ad25-5bda4227d30e","Enabled":true,"GameBoard":{"boardSpaceData":[{"P":"0","T":["B"]},{"P":"0","T":[]},{"P":"0","T":[]},{"P":"2","T":["S"]},{"P":"0","T":[]},{"P":"0","T":[]},{"P":"0","T":[]},{"P":"0","T":["B"]},{"P":"0","T":[]},{"P":"0","T":[]},{"P":"0","T":[]},{"P":"0","T":["S"]},{"P":"0","T":[]},{"P":"0","T":["S"]},{"P":"0","T":["."]},{"P":"0","T":["."]},{"P":"0","T":[]},{"P":"0","T":[]},{"P":"0","T":[]},{"P":"0","T":["S"]},{"P":"0","T":[]},{"P":"0","T":["S"]},{"P":"0","T":[]},{"P":"0","T":[]},{"P":"2","T":[]},{"P":"1","T":[]},{"P":"0","T":[]},{"P":"1","T":["S"]},{"P":"0","T":[]},{"P":"1","T":["S"]},{"P":"0","T":[]},{"P":"0","T":[]},{"P":"0","T":[]},{"P":"0","T":[]},{"P":"1","T":[]},{"P":"0","T":["S"]},{"P":"2","T":["S"]},{"P":"0","T":["S"]},{"P":"0","T":[]},{"P":"0","T":[]},{"P":"0","T":["."]},{"P":"0","T":["."]},{"P":"0","T":["T"]},{"P":"0","T":["S"]},{"P":"0","T":["T"]},{"P":"2","T":["S"]},{"P":"0","T":[]},{"P":"0","T":[]},{"P":"0","T":[]},{"P":"0","T":[]},{"P":"0","T":["S"]},{"P":"2","T":[]},{"P":"1","T":["S"]},{"P":"2","T":[]},{"P":"0","T":[]},{"P":"0","T":[]},{"P":"0","T":["B"]},{"P":"0","T":[]},{"P":"0","T":["."]},{"P":"0","T":[]},{"P":"0","T":[]},{"P":"1","T":[]},{"P":"0","T":[]},{"P":"0","T":["B"]}],"initialMoves":[],"rows":8,"columns":8,"area":2,"id":"b44fbbe2-21ce-4b60-b414-f2ea7c54c364","boardName":"TRAINING_GARDEN Win In 2","enabled":true,"enabledGallery":false,"enabledRealtime":false},"Profile":0,"Boss":0,"FirstTurn":0,"Solution":[{"playerId":1,"playerString":null,"moves":[{"piece":{"conditions":[],"playerId":1,"herdId":0,"UniqueId":"14182cbb-1e1c-4257-b000-fe280d83436c","pieceType":0,"Notation":"1"},"direction":1,"location":4,"moveType":0,"notation":"Move:DOWN4"}],"Notation":"Move:DOWN4","timestamp":0,"uniqueId":"67619a09-c403-4756-8683-ee6758535ee4"},{"playerId":1,"playerString":null,"moves":[{"piece":{"conditions":[],"playerId":1,"herdId":0,"UniqueId":"60cba7c9-2b41-49a1-aaea-76555e7c4236","pieceType":0,"Notation":"1"},"direction":2,"location":3,"moveType":0,"notation":"Move:LEFT3"}],"Notation":"Move:LEFT3","timestamp":0,"uniqueId":"4e5bec12-cd87-45a2-8609-8584c2c6b821"}],"SolutionStateData":{"boardSpaceData":[{"P":"0","T":["B"]},{"P":"0","T":[]},{"P":"0","T":[]},{"P":"2","T":["S"]},{"P":"0","T":[]},{"P":"0","T":[]},{"P":"0","T":[]},{"P":"0","T":["B"]},{"P":"0","T":[]},{"P":"0","T":[]},{"P":"0","T":[]},{"P":"0","T":["S"]},{"P":"0","T":[]},{"P":"0","T":["S"]},{"P":"0","T":["."]},{"P":"0","T":["."]},{"P":"0","T":[]},{"P":"0","T":[]},{"P":"0","T":[]},{"P":"0","T":["S"]},{"P":"0","T":[]},{"P":"0","T":["S"]},{"P":"0","T":[]},{"P":"0","T":[]},{"P":"2","T":[]},{"P":"1","T":[]},{"P":"2","T":[]},{"P":"1","T":["S"]},{"P":"1","T":[]},{"P":"1","T":["S"]},{"P":"1","T":[]},{"P":"0","T":[]},{"P":"0","T":[]},{"P":"0","T":[]},{"P":"1","T":[]},{"P":"0","T":["S"]},{"P":"2","T":["S"]},{"P":"0","T":["S"]},{"P":"0","T":[]},{"P":"0","T":[]},{"P":"0","T":["."]},{"P":"0","T":["."]},{"P":"0","T":["T"]},{"P":"0","T":["S"]},{"P":"0","T":["T"]},{"P":"2","T":["S"]},{"P":"0","T":[]},{"P":"0","T":[]},{"P":"0","T":[]},{"P":"0","T":[]},{"P":"0","T":["S"]},{"P":"2","T":[]},{"P":"1","T":["S"]},{"P":"2","T":[]},{"P":"0","T":[]},{"P":"0","T":[]},{"P":"0","T":["B"]},{"P":"0","T":[]},{"P":"0","T":["."]},{"P":"0","T":[]},{"P":"0","T":[]},{"P":"1","T":[]},{"P":"0","T":[]},{"P":"0","T":["B"]}],"rows":8,"columns":8,"area":2},"GoalType":0,"MoveLimit":2,"Complexity":1841,"StartingMagic":0,"AvailableSpells":[]}