{"boardSpaceData":[{"P":null,"T":["B"]},{"P":null,"T":["S"]},{"P":null,"T":["S"]},{"P":null,"T":["S"]},{"P":null,"T":["S"]},{"P":null,"T":["S"]},{"P":null,"T":["S"]},{"P":null,"T":["B"]},{"P":null,"T":null},{"P":null,"T":null},{"P":null,"T":null},{"P":null,"T":["S"]},{"P":null,"T":null},{"P":null,"T":null},{"P":null,"T":["S"]},{"P":null,"T":null},{"P":null,"T":null},{"P":null,"T":null},{"P":null,"T":["S"]},{"P":null,"T":null},{"P":null,"T":null},{"P":null,"T":["S"]},{"P":null,"T":null},{"P":null,"T":null},{"P":null,"T":null},{"P":null,"T":["S"]},{"P":null,"T":null},{"P":null,"T":null},{"P":null,"T":["S"]},{"P":null,"T":null},{"P":null,"T":null},{"P":null,"T":["S"]},{"P":null,"T":["S"]},{"P":null,"T":null},{"P":null,"T":null},{"P":null,"T":["S"]},{"P":null,"T":null},{"P":null,"T":null},{"P":null,"T":["S"]},{"P":null,"T":null},{"P":null,"T":null},{"P":null,"T":null},{"P":null,"T":["S"]},{"P":null,"T":null},{"P":null,"T":null},{"P":null,"T":["S"]},{"P":null,"T":null},{"P":null,"T":null},{"P":null,"T":null},{"P":null,"T":null},{"P":null,"T":null},{"P":null,"T":null},{"P":null,"T":null},{"P":null,"T":null},{"P":null,"T":null},{"P":null,"T":null},{"P":null,"T":["B"]},{"P":null,"T":["X"]},{"P":null,"T":["X"]},{"P":null,"T":["X"]},{"P":null,"T":["X"]},{"P":null,"T":["X"]},{"P":null,"T":["X"]},{"P":null,"T":["B"]}],"initialMoves":[],"rows":8,"columns":8,"area":4,"id":"f507cc65-0740-425d-a5cd-1664892db2e0","boardName":"Goop Vines","enabled":true,"enabledGallery":true,"enabledRealtime":true}