{"boardSpaceData":[{"P":null,"T":["B"]},{"P":null,"T":null},{"P":null,"T":null},{"P":null,"T":null},{"P":null,"T":null},{"P":null,"T":null},{"P":null,"T":null},{"P":null,"T":["B"]},{"P":null,"T":null},{"P":null,"T":["."]},{"P":null,"T":null},{"P":null,"T":["."]},{"P":null,"T":null},{"P":null,"T":["."]},{"P":null,"T":null},{"P":null,"T":["B"]},{"P":null,"T":null},{"P":null,"T":null},{"P":null,"T":null},{"P":null,"T":null},{"P":null,"T":null},{"P":null,"T":null},{"P":null,"T":null},{"P":null,"T":null},{"P":null,"T":["."]},{"P":null,"T":null},{"P":null,"T":["."]},{"P":null,"T":null},{"P":null,"T":["."]},{"P":null,"T":null},{"P":null,"T":null},{"P":null,"T":["B"]},{"P":null,"T":null},{"P":null,"T":null},{"P":null,"T":null},{"P":null,"T":null},{"P":null,"T":null},{"P":null,"T":null},{"P":null,"T":null},{"P":null,"T":null},{"P":null,"T":null},{"P":null,"T":["."]},{"P":null,"T":null},{"P":null,"T":["."]},{"P":null,"T":null},{"P":null,"T":["."]},{"P":null,"T":null},{"P":null,"T":["B"]},{"P":null,"T":null},{"P":null,"T":null},{"P":null,"T":null},{"P":null,"T":null},{"P":null,"T":null},{"P":null,"T":null},{"P":null,"T":null},{"P":null,"T":null},{"P":null,"T":["B"]},{"P":null,"T":null},{"P":null,"T":null},{"P":null,"T":null},{"P":null,"T":null},{"P":null,"T":null},{"P":null,"T":null},{"P":null,"T":["B"]}],"initialMoves":[],"rows":8,"columns":8,"area":2,"id":"35755177-03f6-4cfb-87fe-8d806bd9fa20","boardName":"Medium_44","enabled":false,"enabledGallery":false,"enabledRealtime":false}