{"boardSpaceData":[{"P":null,"T":["B"]},{"P":null,"T":null},{"P":null,"T":null},{"P":null,"T":null},{"P":null,"T":null},{"P":null,"T":null},{"P":null,"T":null},{"P":null,"T":["B"]},{"P":null,"T":null},{"P":null,"T":null},{"P":null,"T":null},{"P":null,"T":null},{"P":null,"T":null},{"P":null,"T":null},{"P":null,"T":null},{"P":null,"T":null},{"P":null,"T":null},{"P":null,"T":null},{"P":null,"T":["AR"]},{"P":null,"T":null},{"P":null,"T":null},{"P":null,"T":["AD"]},{"P":null,"T":null},{"P":null,"T":null},{"P":null,"T":null},{"P":null,"T":null},{"P":null,"T":null},{"P":null,"T":null},{"P":null,"T":null},{"P":null,"T":null},{"P":null,"T":null},{"P":null,"T":null},{"P":null,"T":null},{"P":null,"T":null},{"P":null,"T":null},{"P":null,"T":null},{"P":null,"T":null},{"P":null,"T":null},{"P":null,"T":null},{"P":null,"T":null},{"P":null,"T":null},{"P":null,"T":null},{"P":null,"T":["AU"]},{"P":null,"T":null},{"P":null,"T":null},{"P":null,"T":["AL"]},{"P":null,"T":null},{"P":null,"T":null},{"P":null,"T":null},{"P":null,"T":null},{"P":null,"T":null},{"P":null,"T":null},{"P":null,"T":null},{"P":null,"T":null},{"P":null,"T":null},{"P":null,"T":null},{"P":null,"T":["B"]},{"P":null,"T":null},{"P":null,"T":null},{"P":null,"T":null},{"P":null,"T":null},{"P":null,"T":null},{"P":null,"T":null},{"P":null,"T":["B"]}],"initialMoves":[],"rows":8,"columns":8,"area":2,"id":"6c2f8d5d-b79b-4409-896b-b51238a26024","boardName":"Simple_07","enabled":false,"enabledGallery":false,"enabledRealtime":false}