{"boardSpaceData":[{"P":"0","T":["B"]},{"P":"0","T":["i"]},{"P":"0","T":["i"]},{"P":"0","T":["i"]},{"P":"1","T":["i"]},{"P":"0","T":["I"]},{"P":"0","T":[]},{"P":"0","T":["B"]},{"P":"0","T":[]},{"P":"0","T":["i"]},{"P":"0","T":["i"]},{"P":"0","T":["i"]},{"P":"0","T":["i"]},{"P":"0","T":[]},{"P":"0","T":[]},{"P":"0","T":[]},{"P":"0","T":[]},{"P":"0","T":["i"]},{"P":"0","T":["i"]},{"P":"0","T":["i"]},{"P":"1","T":["i"]},{"P":"0","T":[]},{"P":"0","T":[]},{"P":"0","T":[]},{"P":"0","T":[]},{"P":"0","T":["i"]},{"P":"0","T":["i"]},{"P":"0","T":["i"]},{"P":"2","T":["i"]},{"P":"2","T":[]},{"P":"2","T":[]},{"P":"0","T":[]},{"P":"0","T":[]},{"P":"0","T":["i"]},{"P":"0","T":["i"]},{"P":"0","T":["i"]},{"P":"0","T":["i"]},{"P":"1","T":[]},{"P":"1","T":[]},{"P":"2","T":[]},{"P":"0","T":[]},{"P":"0","T":["i"]},{"P":"0","T":["i"]},{"P":"0","T":["i"]},{"P":"0","T":["i"]},{"P":"0","T":[]},{"P":"0","T":[]},{"P":"0","T":[]},{"P":"0","T":[]},{"P":"0","T":[]},{"P":"0","T":["i"]},{"P":"0","T":["I"]},{"P":"0","T":["i"]},{"P":"0","T":["I"]},{"P":"0","T":[]},{"P":"0","T":["I"]},{"P":"0","T":["B"]},{"P":"-1","T":["i"]},{"P":"0","T":["i"]},{"P":"0","T":["i"]},{"P":"0","T":["i"]},{"P":"0","T":[]},{"P":"0","T":[]},{"P":"0","T":["B"]}],"initialMoves":[],"rows":8,"columns":8,"area":16,"id":"d83647d4-3062-407f-9ffb-4facb6d03d59","boardName":"ICE_PALACE 2 Win In 3 ActivePlayer=1","enabled":true,"enabledGallery":false,"enabledRealtime":false}